MANIFEST.in
setup.cfg
setup.py
docs/man/yadtshell.1.man.gz
scripts/analyze-target
scripts/init-yadtshell
scripts/sync_logs_of_all_targets
scripts/sync_logs_of_target.py
scripts/yadtshell
scripts/yadtshell-activate
scripts/yadtshellrc
yadtshell/TerminalController.py
yadtshell/__init__.py
yadtshell/actionmanager.py
yadtshell/actions.py
yadtshell/broadcast.py
yadtshell/commandline.py
yadtshell/components.py
yadtshell/constants.py
yadtshell/defer.py
yadtshell/dump.py
yadtshell/helper.py
yadtshell/info.py
yadtshell/loggingtools.py
yadtshell/metalogic.py
yadtshell/restart.py
yadtshell/settings.py
yadtshell/status.py
yadtshell/twisted.py
yadtshell/update.py
yadtshell/uri.py
yadtshell/util.py
yadtshell/validation.py
yadtshell.egg-info/PKG-INFO
yadtshell.egg-info/SOURCES.txt
yadtshell.egg-info/dependency_links.txt
yadtshell.egg-info/entry_points.txt
yadtshell.egg-info/requires.txt
yadtshell.egg-info/top_level.txt
yadtshell.egg-info/zip-safe