Metadata-Version: 1.1
Name: yadtshell
Version: 1.9.1
Summary: YADT - an Augmented Deployment Tool - The Shell Part
Home-page: https://github.com/yadt/yadtshell
Author: Arne Hilmann, Marcel Wolf, Maximilien Riehl
Author-email: arne.hilmann@gmail.com, marcel.wolf@me.com, max@riehl.io
License: GNU GPL v3
Platform: UNKNOWN
Classifier: Development Status :: 4 - Beta
Classifier: Environment :: Console
Classifier: Intended Audience :: Developers
Classifier: Intended Audience :: System Administrators
Classifier: License :: OSI Approved :: GNU General Public License (GPL)
Classifier: Programming Language :: Python
Classifier: Topic :: System :: Networking
Classifier: Topic :: System :: Software Distribution
Classifier: Topic :: System :: Systems Administration
